setup.py
pypi/__init__.py
pypi.trashfinder.egg-info/PKG-INFO
pypi.trashfinder.egg-info/SOURCES.txt
pypi.trashfinder.egg-info/dependency_links.txt
pypi.trashfinder.egg-info/namespace_packages.txt
pypi.trashfinder.egg-info/requires.txt
pypi.trashfinder.egg-info/top_level.txt
pypi/trashfinder/__init__.py
pypi/trashfinder/cli.py