Metadata-Version: 1.0
Name: pypi.trashfinder
Version: 0.0.3
Summary: This is a fork of zopyx.trashfinder, with modifications made to make integration with pythonpackages.com easier. It is not intended to be used outside of pythonpackages.com. For a command line trash finder, please install zopyx.trashfinder.
Home-page: UNKNOWN
Author: UNKNOWN
Author-email: UNKNOWN
License: UNKNOWN
Platform: UNKNOWN
